{"stat.walkOneCm":132679,"stat.useItem.minecraft.sapling":1,"stat.leaveGame":3,"stat.damageTaken":345,"stat.useItem.minecraft.chicken":1,"stat.useItem.minecraft.apple":1,"stat.flyOneCm":4818,"stat.deaths":1,"stat.jump":377,"stat.swimOneCm":3392,"stat.mineBlock.minecraft.leaves":24,"stat.playOneMinute":23172,"stat.fallOneCm":7641,"stat.damageDealt":150,"stat.timeSinceDeath":11695,"stat.useItem.minecraft.dirt":6,"stat.sprintOneCm":24316,"stat.mineBlock.minecraft.dirt":3,"achievement.exploreAllBiomes":{"value":0,"progress":["Beach","Forest","Plains","Deep Ocean"]},"stat.diveOneCm":17478}